nonebot_plugin_weiweibot-0.2.3.dist-info/METADATA
nonebot_plugin_weiweibot-0.2.3.dist-info/WHEEL
nonebot_plugin_weiweibot-0.2.3.dist-info/entry_points.txt
nonebot_plugin_weiweibot-0.2.3.dist-info/licenses/LICENSE
plug/nonebot-plugin-weiweibot/__init__.py
plug/nonebot-plugin-weiweibot/config.py
plug/nonebot-plugin-weiweibot/search.py
plug/nonebot-plugin-weiweibot/store.py
plug/nonebot-plugin-weiweibot/utils.py
nonebot_plugin_weiweibot-0.2.3.dist-info/RECORD
