Metadata-Version: 2.1
Name: nonebot-plugin-weiweibot
Version: 0.2.3
Summary: a simple weiwei bot
Keywords: nonebot
Author-Email: Alesso <intro@j4cka.cc>, Divinity <1342602392@qq.com>
License: MIT
Project-URL: homepage, https://github.com/SwedishDoveCooker/nonebot-plugin-weiweibot
Project-URL: repository, https://github.com/SwedishDoveCooker/nonebot-plugin-weiweibot
Requires-Python: >=3.12
Requires-Dist: nonebot2>=2.2.0
Requires-Dist: nonebot-adapter-onebot>=2.1.3
Requires-Dist: python-gnupg>=0.5.4
Requires-Dist: algoliasearch>=4.22.1
Requires-Dist: filetype>=1.2.0
Requires-Dist: httpx>=0.28.1
